{
  "$schema": "https://developer.microsoft.com/json-schemas/fabric/item/report/definition/visualContainer/2.0.0/schema.json",
  "name": "653b57e5c9ba254ec575",
  "position": {
    "x": 32.395132942767013,
    "y": 369.6367733213159,
    "z": 8001,
    "height": 323.12068499324016,
    "width": 1221.8779630464173,
    "tabOrder": 8001
  },
  "visual": {
    "visualType": "pivotTable",
    "query": {
      "queryState": {
        "Rows": {
          "projections": [
            {
              "field": {
                "Column": {
                  "Expression": {
                    "SourceRef": {
                      "Entity": "Product"
                    }
                  },
                  "Property": "Category"
                }
              },
              "queryRef": "Product.Category",
              "nativeQueryRef": "Category",
              "active": true
            },
            {
              "field": {
                "Column": {
                  "Expression": {
                    "SourceRef": {
                      "Entity": "Product"
                    }
                  },
                  "Property": "Product"
                }
              },
              "queryRef": "Product.Product",
              "nativeQueryRef": "Product",
              "active": false
            }
          ]
        },
        "Values": {
          "projections": [
            {
              "field": {
                "Measure": {
                  "Expression": {
                    "SourceRef": {
                      "Entity": "Sales"
                    }
                  },
                  "Property": "# Sales"
                }
              },
              "queryRef": "Sales.# Sales",
              "nativeQueryRef": "# Sales"
            },
            {
              "field": {
                "Measure": {
                  "Expression": {
                    "SourceRef": {
                      "Entity": "Sales"
                    }
                  },
                  "Property": "Sales Amount"
                }
              },
              "queryRef": "Sales.Sales Amount",
              "nativeQueryRef": "Sales Amount"
            },
            {
              "field": {
                "Measure": {
                  "Expression": {
                    "SourceRef": {
                      "Entity": "Sales"
                    }
                  },
                  "Property": "Sales Amount (12M average)"
                }
              },
              "queryRef": "Sales.Sales Amount (12M average)",
              "nativeQueryRef": "Sales Amount (12M average)"
            },
            {
              "field": {
                "Measure": {
                  "Expression": {
                    "SourceRef": {
                      "Entity": "Sales"
                    }
                  },
                  "Property": "Sales Amount (6M average)"
                }
              },
              "queryRef": "Sales.Sales Amount (6M average)",
              "nativeQueryRef": "Sales Amount (6M average)"
            },
            {
              "field": {
                "Measure": {
                  "Expression": {
                    "SourceRef": {
                      "Entity": "Sales"
                    }
                  },
                  "Property": "Sales Amount (LY)"
                }
              },
              "queryRef": "Sales.Sales Amount (LY)",
              "nativeQueryRef": "Sales Amount (LY)"
            },
            {
              "field": {
                "Measure": {
                  "Expression": {
                    "SourceRef": {
                      "Entity": "Sales"
                    }
                  },
                  "Property": "Sales Amount Avg per Day"
                }
              },
              "queryRef": "Sales.Sales Amount Avg per Day",
              "nativeQueryRef": "Sales Amount Avg per Day"
            },
            {
              "field": {
                "Measure": {
                  "Expression": {
                    "SourceRef": {
                      "Entity": "Sales"
                    }
                  },
                  "Property": "Sales Qty"
                }
              },
              "queryRef": "Sales.Sales Qty",
              "nativeQueryRef": "Sales Qty"
            }
          ]
        }
      }
    },
    "drillFilterOtherVisuals": true
  }
}